bio_rtd/__init__.py
bio_rtd/adj_par.py
bio_rtd/core.py
bio_rtd/inlet.py
bio_rtd/logger.py
bio_rtd/pdf.py
bio_rtd/peak_fitting.py
bio_rtd/peak_shapes.py
bio_rtd/chromatography/__init__.py
bio_rtd/chromatography/bt_curve.py
bio_rtd/chromatography/bt_load.py
bio_rtd/uo/__init__.py
bio_rtd/uo/fc_uo.py
bio_rtd/uo/sc_uo.py
bio_rtd/uo/special_uo.py
bio_rtd/uo/surge_tank.py
bio_rtd/utils/__init__.py
bio_rtd/utils/convolution.py
bio_rtd/utils/vectors.py
bio_rtd-0.7.2.dist-info/LICENSE.md
bio_rtd-0.7.2.dist-info/METADATA
bio_rtd-0.7.2.dist-info/WHEEL
bio_rtd-0.7.2.dist-info/top_level.txt
bio_rtd-0.7.2.dist-info/RECORD
