Metadata-Version: 2.1
Name: bio-rtd
Version: 0.7.2
Summary: Library for modeling residence time distributions (RTD) of integrated continuous biomanufacturing processes.
Home-page: https://github.com/open-biotech/bio-rtd/
Author: Jure Sencar
Author-email: jure@timetools.eu
License: MIT
Project-URL: Bug Tracker, https://github.com/open-biotech/bio-rtd/issues/
Project-URL: Documentation, https://open-biotech.github.io/bio-rtd-docs/
Project-URL: Source Code, https://github.com/open-biotech/bio-rtd/
Keywords: residence time distribution,biomanufacturing
Platform: UNKNOWN
Classifier: Development Status :: 4 - Beta
Classifier: Intended Audience :: Developers
Classifier: Topic :: Scientific/Engineering
Classifier: Intended Audience :: Healthcare Industry
Classifier: Intended Audience :: Science/Research
Classifier: Intended Audience :: Manufacturing
Classifier: License :: OSI Approved :: MIT License
Classifier: Programming Language :: Python :: 3
Classifier: Programming Language :: Python :: 3.7
Requires-Python: >=3.7
Requires-Dist: numpy
Requires-Dist: scipy
